[
  {
    "cluster_id": 0,
    "persona": "tech_male",
    "catch_copy": "Apple WatchとAirPodsを同時に充電できるワイヤレス充電器。 快適に使える高品質モデル。",
    "alts": [
      "性能を研ぎ澄ませた一台、日々の効率を高める設計。",
      "スマートな操作感で、ビジネスもプライベートも快適に。",
      "機能美が光る、無駄のないデザイン。",
      "性能を研ぎ澄ませた一台、日々の効率を高める設計。",
      "スマートな操作感で、ビジネスもプライベートも快適に。",
      "機能美が光る、無駄のないデザイン。",
      "性能を研ぎ澄ませた一台、日々の効率を高める設計。",
      "スマートな操作感で、ビジネスもプライベートも快適に。",
      "機能美が光る、無駄のないデザイン。",
      "性能を研ぎ澄ませた一台、日々の効率を高める設計。",
      "スマートな操作感で、ビジネスもプライベートも快適に。",
      "機能美が光る、無駄のないデザイン。",
      "性能を研ぎ澄ませた一台、日々の効率を高める設計。",
      "スマートな操作感で、ビジネスもプライベートも快適に。",
      "機能美が光る、無駄のないデザイン。",
      "性能を研ぎ澄ませた一台、日々の効率を高める設計。",
      "スマートな操作感で、ビジネスもプライベートも快適に。",
      "機能美が光る、無駄のないデザイン。",
      "性能を研ぎ澄ませた一台、日々の効率を高める設計。",
      "スマートな操作感で、ビジネスもプライベートも快適に。"
    ],
    "brand_tone": "Honest_Wit"
  },
  {
    "cluster_id": 1,
    "persona": "default",
    "catch_copy": "かわいさと耐衝撃性を兼ね備えたiPhone13プロケースで、スマホをしっかり守ろう。 快適に使える高品質モデル。",
    "alts": [
      "シーンを選ばず使えるシンプルな一品。",
      "日常をより快適にする、使いやすさを追求。",
      "デザインと機能を両立したアイテム。",
      "シーンを選ばず使えるシンプルな一品。",
      "日常をより快適にする、使いやすさを追求。",
      "デザインと機能を両立したアイテム。",
      "シーンを選ばず使えるシンプルな一品。",
      "日常をより快適にする、使いやすさを追求。",
      "デザインと機能を両立したアイテム。",
      "シーンを選ばず使えるシンプルな一品。",
      "日常をより快適にする、使いやすさを追求。",
      "デザインと機能を両立したアイテム。",
      "シーンを選ばず使えるシンプルな一品。",
      "日常をより快適にする、使いやすさを追求。",
      "デザインと機能を両立したアイテム。",
      "シーンを選ばず使えるシンプルな一品。",
      "日常をより快適にする、使いやすさを追求。",
      "デザインと機能を両立したアイテム。",
      "シーンを選ばず使えるシンプルな一品。",
      "日常をより快適にする、使いやすさを追求。"
    ],
    "brand_tone": "Honest_Wit"
  },
  {
    "cluster_id": 2,
    "persona": "default",
    "catch_copy": "iPhone13プロマックス専用のブルーライトカットフィルム。 快適に使える高品質モデル。",
    "alts": [
      "シーンを選ばず使えるシンプルな一品。",
      "日常をより快適にする、使いやすさを追求。",
      "デザインと機能を両立したアイテム。",
      "シーンを選ばず使えるシンプルな一品。",
      "日常をより快適にする、使いやすさを追求。",
      "デザインと機能を両立したアイテム。",
      "シーンを選ばず使えるシンプルな一品。",
      "日常をより快適にする、使いやすさを追求。",
      "デザインと機能を両立したアイテム。",
      "シーンを選ばず使えるシンプルな一品。",
      "日常をより快適にする、使いやすさを追求。",
      "デザインと機能を両立したアイテム。",
      "シーンを選ばず使えるシンプルな一品。",
      "日常をより快適にする、使いやすさを追求。",
      "デザインと機能を両立したアイテム。",
      "シーンを選ばず使えるシンプルな一品。",
      "日常をより快適にする、使いやすさを追求。",
      "デザインと機能を両立したアイテム。",
      "シーンを選ばず使えるシンプルな一品。",
      "日常をより快適にする、使いやすさを追求。"
    ],
    "brand_tone": "Honest_Wit"
  },
  {
    "cluster_id": 3,
    "persona": "default",
    "catch_copy": "指紋がつかないiPhone画面を守る高性能ガラスフィルム。 快適に使える高品質モデル。",
    "alts": [
      "シーンを選ばず使えるシンプルな一品。",
      "日常をより快適にする、使いやすさを追求。",
      "デザインと機能を両立したアイテム。",
      "シーンを選ばず使えるシンプルな一品。",
      "日常をより快適にする、使いやすさを追求。",
      "デザインと機能を両立したアイテム。",
      "シーンを選ばず使えるシンプルな一品。",
      "日常をより快適にする、使いやすさを追求。",
      "デザインと機能を両立したアイテム。",
      "シーンを選ばず使えるシンプルな一品。",
      "日常をより快適にする、使いやすさを追求。",
      "デザインと機能を両立したアイテム。",
      "シーンを選ばず使えるシンプルな一品。",
      "日常をより快適にする、使いやすさを追求。",
      "デザインと機能を両立したアイテム。",
      "シーンを選ばず使えるシンプルな一品。",
      "日常をより快適にする、使いやすさを追求。",
      "デザインと機能を両立したアイテム。",
      "シーンを選ばず使えるシンプルな一品。",
      "日常をより快適にする、使いやすさを追求。"
    ],
    "brand_tone": "Honest_Wit"
  },
  {
    "cluster_id": 4,
    "persona": "default",
    "catch_copy": "楽天1位上品で知的なおしゃれさなワイヤレスイヤホンアクセサリー。 快適に使える高品質モデル。",
    "alts": [
      "シーンを選ばず使えるシンプルな一品。",
      "日常をより快適にする、使いやすさを追求。",
      "デザインと機能を両立したアイテム。",
      "シーンを選ばず使えるシンプルな一品。",
      "日常をより快適にする、使いやすさを追求。",
      "デザインと機能を両立したアイテム。",
      "シーンを選ばず使えるシンプルな一品。",
      "日常をより快適にする、使いやすさを追求。",
      "デザインと機能を両立したアイテム。",
      "シーンを選ばず使えるシンプルな一品。",
      "日常をより快適にする、使いやすさを追求。",
      "デザインと機能を両立したアイテム。",
      "シーンを選ばず使えるシンプルな一品。",
      "日常をより快適にする、使いやすさを追求。",
      "デザインと機能を両立したアイテム。",
      "シーンを選ばず使えるシンプルな一品。",
      "日常をより快適にする、使いやすさを追求。",
      "デザインと機能を両立したアイテム。",
      "シーンを選ばず使えるシンプルな一品。",
      "日常をより快適にする、使いやすさを追求。"
    ],
    "brand_tone": "Honest_Wit"
  },
  {
    "cluster_id": 5,
    "persona": "office",
    "catch_copy": "ビジネスに最適な静かに上質を感じさせる感あふれるアップルウォッチバンド。 快適に使える高品質モデル。",
    "alts": [
      "洗練された印象を与える、知的なデザイン。",
      "毎日の業務をスマートに支える実用性。",
      "オフィスワークに心地よい集中環境を提供。",
      "洗練された印象を与える、知的なデザイン。",
      "毎日の業務をスマートに支える実用性。",
      "オフィスワークに心地よい集中環境を提供。",
      "洗練された印象を与える、知的なデザイン。",
      "毎日の業務をスマートに支える実用性。",
      "オフィスワークに心地よい集中環境を提供。",
      "洗練された印象を与える、知的なデザイン。",
      "毎日の業務をスマートに支える実用性。",
      "オフィスワークに心地よい集中環境を提供。",
      "洗練された印象を与える、知的なデザイン。",
      "毎日の業務をスマートに支える実用性。",
      "オフィスワークに心地よい集中環境を提供。",
      "洗練された印象を与える、知的なデザイン。",
      "毎日の業務をスマートに支える実用性。",
      "オフィスワークに心地よい集中環境を提供。",
      "洗練された印象を与える、知的なデザイン。",
      "毎日の業務をスマートに支える実用性。"
    ],
    "brand_tone": "Honest_Wit"
  },
  {
    "cluster_id": 6,
    "persona": "default",
    "catch_copy": "上品で知的なおしゃれさで快適なアップルウォッチバンドを手に入れよう。 快適に使える高品質モデル。",
    "alts": [
      "シーンを選ばず使えるシンプルな一品。",
      "日常をより快適にする、使いやすさを追求。",
      "デザインと機能を両立したアイテム。",
      "シーンを選ばず使えるシンプルな一品。",
      "日常をより快適にする、使いやすさを追求。",
      "デザインと機能を両立したアイテム。",
      "シーンを選ばず使えるシンプルな一品。",
      "日常をより快適にする、使いやすさを追求。",
      "デザインと機能を両立したアイテム。",
      "シーンを選ばず使えるシンプルな一品。",
      "日常をより快適にする、使いやすさを追求。",
      "デザインと機能を両立したアイテム。",
      "シーンを選ばず使えるシンプルな一品。",
      "日常をより快適にする、使いやすさを追求。",
      "デザインと機能を両立したアイテム。",
      "シーンを選ばず使えるシンプルな一品。",
      "日常をより快適にする、使いやすさを追求。",
      "デザインと機能を両立したアイテム。",
      "シーンを選ばず使えるシンプルな一品。",
      "日常をより快適にする、使いやすさを追求。"
    ],
    "brand_tone": "Honest_Wit"
  },
  {
    "cluster_id": 7,
    "persona": "tech_male",
    "catch_copy": "スタイリッシュで機能的なMacBook Proケースが、あなたの魅力を引き立てます。 快適に使える高品質モデル。",
    "alts": [
      "性能を研ぎ澄ませた一台、日々の効率を高める設計。",
      "スマートな操作感で、ビジネスもプライベートも快適に。",
      "機能美が光る、無駄のないデザイン。",
      "性能を研ぎ澄ませた一台、日々の効率を高める設計。",
      "スマートな操作感で、ビジネスもプライベートも快適に。",
      "機能美が光る、無駄のないデザイン。",
      "性能を研ぎ澄ませた一台、日々の効率を高める設計。",
      "スマートな操作感で、ビジネスもプライベートも快適に。",
      "機能美が光る、無駄のないデザイン。",
      "性能を研ぎ澄ませた一台、日々の効率を高める設計。",
      "スマートな操作感で、ビジネスもプライベートも快適に。",
      "機能美が光る、無駄のないデザイン。",
      "性能を研ぎ澄ませた一台、日々の効率を高める設計。",
      "スマートな操作感で、ビジネスもプライベートも快適に。",
      "機能美が光る、無駄のないデザイン。",
      "性能を研ぎ澄ませた一台、日々の効率を高める設計。",
      "スマートな操作感で、ビジネスもプライベートも快適に。",
      "機能美が光る、無駄のないデザイン。",
      "性能を研ぎ澄ませた一台、日々の効率を高める設計。",
      "スマートな操作感で、ビジネスもプライベートも快適に。"
    ],
    "brand_tone": "Honest_Wit"
  },
  {
    "cluster_id": 8,
    "persona": "home_life",
    "catch_copy": "エアーポッズを可愛く守る上品で知的なおしゃれさなシリコンケースで収納。 快適に使える高品質モデル。",
    "alts": [
      "暮らしに寄り添う穏やかなデザイン。",
      "毎日に小さな心地よさを与えるアイテム。",
      "空間をやさしく整えるシンプルな佇まい。",
      "暮らしに寄り添う穏やかなデザイン。",
      "毎日に小さな心地よさを与えるアイテム。",
      "空間をやさしく整えるシンプルな佇まい。",
      "暮らしに寄り添う穏やかなデザイン。",
      "毎日に小さな心地よさを与えるアイテム。",
      "空間をやさしく整えるシンプルな佇まい。",
      "暮らしに寄り添う穏やかなデザイン。",
      "毎日に小さな心地よさを与えるアイテム。",
      "空間をやさしく整えるシンプルな佇まい。",
      "暮らしに寄り添う穏やかなデザイン。",
      "毎日に小さな心地よさを与えるアイテム。",
      "空間をやさしく整えるシンプルな佇まい。",
      "暮らしに寄り添う穏やかなデザイン。",
      "毎日に小さな心地よさを与えるアイテム。",
      "空間をやさしく整えるシンプルな佇まい。",
      "暮らしに寄り添う穏やかなデザイン。",
      "毎日に小さな心地よさを与えるアイテム。"
    ],
    "brand_tone": "Honest_Wit"
  },
  {
    "cluster_id": 9,
    "persona": "default",
    "catch_copy": "最強硬度9Hのフィルムで、ゲームを思いっきり楽しもう。 快適に使える高品質モデル。",
    "alts": [
      "シーンを選ばず使えるシンプルな一品。",
      "日常をより快適にする、使いやすさを追求。",
      "デザインと機能を両立したアイテム。",
      "シーンを選ばず使えるシンプルな一品。",
      "日常をより快適にする、使いやすさを追求。",
      "デザインと機能を両立したアイテム。",
      "シーンを選ばず使えるシンプルな一品。",
      "日常をより快適にする、使いやすさを追求。",
      "デザインと機能を両立したアイテム。",
      "シーンを選ばず使えるシンプルな一品。",
      "日常をより快適にする、使いやすさを追求。",
      "デザインと機能を両立したアイテム。",
      "シーンを選ばず使えるシンプルな一品。",
      "日常をより快適にする、使いやすさを追求。",
      "デザインと機能を両立したアイテム。",
      "シーンを選ばず使えるシンプルな一品。",
      "日常をより快適にする、使いやすさを追求。",
      "デザインと機能を両立したアイテム。",
      "シーンを選ばず使えるシンプルな一品。",
      "日常をより快適にする、使いやすさを追求。"
    ],
    "brand_tone": "Honest_Wit"
  },
  {
    "cluster_id": 10,
    "persona": "default",
    "catch_copy": "今だけフィルムプレゼントiPhone 12 Pro Maxケースで大切なスマホを守ろう。 快適に使える高品質モデル。",
    "alts": [
      "シーンを選ばず使えるシンプルな一品。",
      "日常をより快適にする、使いやすさを追求。",
      "デザインと機能を両立したアイテム。",
      "シーンを選ばず使えるシンプルな一品。",
      "日常をより快適にする、使いやすさを追求。",
      "デザインと機能を両立したアイテム。",
      "シーンを選ばず使えるシンプルな一品。",
      "日常をより快適にする、使いやすさを追求。",
      "デザインと機能を両立したアイテム。",
      "シーンを選ばず使えるシンプルな一品。",
      "日常をより快適にする、使いやすさを追求。",
      "デザインと機能を両立したアイテム。",
      "シーンを選ばず使えるシンプルな一品。",
      "日常をより快適にする、使いやすさを追求。",
      "デザインと機能を両立したアイテム。",
      "シーンを選ばず使えるシンプルな一品。",
      "日常をより快適にする、使いやすさを追求。",
      "デザインと機能を両立したアイテム。",
      "シーンを選ばず使えるシンプルな一品。",
      "日常をより快適にする、使いやすさを追求。"
    ],
    "brand_tone": "Honest_Wit"
  },
  {
    "cluster_id": 11,
    "persona": "default",
    "catch_copy": "360度回転で使いやすい、軽量でスタイリッシュなiPadケース。 快適に使える高品質モデル。",
    "alts": [
      "シーンを選ばず使えるシンプルな一品。",
      "日常をより快適にする、使いやすさを追求。",
      "デザインと機能を両立したアイテム。",
      "シーンを選ばず使えるシンプルな一品。",
      "日常をより快適にする、使いやすさを追求。",
      "デザインと機能を両立したアイテム。",
      "シーンを選ばず使えるシンプルな一品。",
      "日常をより快適にする、使いやすさを追求。",
      "デザインと機能を両立したアイテム。",
      "シーンを選ばず使えるシンプルな一品。",
      "日常をより快適にする、使いやすさを追求。",
      "デザインと機能を両立したアイテム。",
      "シーンを選ばず使えるシンプルな一品。",
      "日常をより快適にする、使いやすさを追求。",
      "デザインと機能を両立したアイテム。",
      "シーンを選ばず使えるシンプルな一品。",
      "日常をより快適にする、使いやすさを追求。",
      "デザインと機能を両立したアイテム。",
      "シーンを選ばず使えるシンプルな一品。",
      "日常をより快適にする、使いやすさを追求。"
    ],
    "brand_tone": "Honest_Wit"
  },
  {
    "cluster_id": 12,
    "persona": "default",
    "catch_copy": "大人の女性に最適なフィットネス水着で、ジムも海も楽しもう。 快適に使える高品質モデル。",
    "alts": [
      "シーンを選ばず使えるシンプルな一品。",
      "日常をより快適にする、使いやすさを追求。",
      "デザインと機能を両立したアイテム。",
      "シーンを選ばず使えるシンプルな一品。",
      "日常をより快適にする、使いやすさを追求。",
      "デザインと機能を両立したアイテム。",
      "シーンを選ばず使えるシンプルな一品。",
      "日常をより快適にする、使いやすさを追求。",
      "デザインと機能を両立したアイテム。",
      "シーンを選ばず使えるシンプルな一品。",
      "日常をより快適にする、使いやすさを追求。",
      "デザインと機能を両立したアイテム。",
      "シーンを選ばず使えるシンプルな一品。",
      "日常をより快適にする、使いやすさを追求。",
      "デザインと機能を両立したアイテム。",
      "シーンを選ばず使えるシンプルな一品。",
      "日常をより快適にする、使いやすさを追求。",
      "デザインと機能を両立したアイテム。",
      "シーンを選ばず使えるシンプルな一品。",
      "日常をより快適にする、使いやすさを追求。"
    ],
    "brand_tone": "Honest_Wit"
  },
  {
    "cluster_id": 13,
    "persona": "fashion_female",
    "catch_copy": "大きいサイズも揃った、理にかなったシンプルさでさりげなく愛らしいフィットネス水着を今すぐチェック。 快適に使える高品質モデル。",
    "alts": [
      "軽やかに日常を彩る、心ときめくデザイン。",
      "やさしい光をまとうような、上品な質感。",
      "自然体のあなたを引き立てる洗練されたスタイル。",
      "軽やかに日常を彩る、心ときめくデザイン。",
      "やさしい光をまとうような、上品な質感。",
      "自然体のあなたを引き立てる洗練されたスタイル。",
      "軽やかに日常を彩る、心ときめくデザイン。",
      "やさしい光をまとうような、上品な質感。",
      "自然体のあなたを引き立てる洗練されたスタイル。",
      "軽やかに日常を彩る、心ときめくデザイン。",
      "やさしい光をまとうような、上品な質感。",
      "自然体のあなたを引き立てる洗練されたスタイル。",
      "軽やかに日常を彩る、心ときめくデザイン。",
      "やさしい光をまとうような、上品な質感。",
      "自然体のあなたを引き立てる洗練されたスタイル。",
      "軽やかに日常を彩る、心ときめくデザイン。",
      "やさしい光をまとうような、上品な質感。",
      "自然体のあなたを引き立てる洗練されたスタイル。",
      "軽やかに日常を彩る、心ときめくデザイン。",
      "やさしい光をまとうような、上品な質感。"
    ],
    "brand_tone": "Honest_Wit"
  },
  {
    "cluster_id": 14,
    "persona": "default",
    "catch_copy": "楽天1位子どもにぴったりの水着セットで、楽しい夏を満喫しよう。 快適に使える高品質モデル。",
    "alts": [
      "シーンを選ばず使えるシンプルな一品。",
      "日常をより快適にする、使いやすさを追求。",
      "デザインと機能を両立したアイテム。",
      "シーンを選ばず使えるシンプルな一品。",
      "日常をより快適にする、使いやすさを追求。",
      "デザインと機能を両立したアイテム。",
      "シーンを選ばず使えるシンプルな一品。",
      "日常をより快適にする、使いやすさを追求。",
      "デザインと機能を両立したアイテム。",
      "シーンを選ばず使えるシンプルな一品。",
      "日常をより快適にする、使いやすさを追求。",
      "デザインと機能を両立したアイテム。",
      "シーンを選ばず使えるシンプルな一品。",
      "日常をより快適にする、使いやすさを追求。",
      "デザインと機能を両立したアイテム。",
      "シーンを選ばず使えるシンプルな一品。",
      "日常をより快適にする、使いやすさを追求。",
      "デザインと機能を両立したアイテム。",
      "シーンを選ばず使えるシンプルな一品。",
      "日常をより快適にする、使いやすさを追求。"
    ],
    "brand_tone": "Honest_Wit"
  },
  {
    "cluster_id": 15,
    "persona": "home_life",
    "catch_copy": "楽天1位体温も測れるタッチレスオートソープディスペンサー。 快適に使える高品質モデル。",
    "alts": [
      "暮らしに寄り添う穏やかなデザイン。",
      "毎日に小さな心地よさを与えるアイテム。",
      "空間をやさしく整えるシンプルな佇まい。",
      "暮らしに寄り添う穏やかなデザイン。",
      "毎日に小さな心地よさを与えるアイテム。",
      "空間をやさしく整えるシンプルな佇まい。",
      "暮らしに寄り添う穏やかなデザイン。",
      "毎日に小さな心地よさを与えるアイテム。",
      "空間をやさしく整えるシンプルな佇まい。",
      "暮らしに寄り添う穏やかなデザイン。",
      "毎日に小さな心地よさを与えるアイテム。",
      "空間をやさしく整えるシンプルな佇まい。",
      "暮らしに寄り添う穏やかなデザイン。",
      "毎日に小さな心地よさを与えるアイテム。",
      "空間をやさしく整えるシンプルな佇まい。",
      "暮らしに寄り添う穏やかなデザイン。",
      "毎日に小さな心地よさを与えるアイテム。",
      "空間をやさしく整えるシンプルな佇まい。",
      "暮らしに寄り添う穏やかなデザイン。",
      "毎日に小さな心地よさを与えるアイテム。"
    ],
    "brand_tone": "Honest_Wit"
  },
  {
    "cluster_id": 16,
    "persona": "default",
    "catch_copy": "上品で知的なおしゃれさで持ち運びに考え抜かれた便利さな犬用折りたたみフードボール。 快適に使える高品質モデル。",
    "alts": [
      "シーンを選ばず使えるシンプルな一品。",
      "日常をより快適にする、使いやすさを追求。",
      "デザインと機能を両立したアイテム。",
      "シーンを選ばず使えるシンプルな一品。",
      "日常をより快適にする、使いやすさを追求。",
      "デザインと機能を両立したアイテム。",
      "シーンを選ばず使えるシンプルな一品。",
      "日常をより快適にする、使いやすさを追求。",
      "デザインと機能を両立したアイテム。",
      "シーンを選ばず使えるシンプルな一品。",
      "日常をより快適にする、使いやすさを追求。",
      "デザインと機能を両立したアイテム。",
      "シーンを選ばず使えるシンプルな一品。",
      "日常をより快適にする、使いやすさを追求。",
      "デザインと機能を両立したアイテム。",
      "シーンを選ばず使えるシンプルな一品。",
      "日常をより快適にする、使いやすさを追求。",
      "デザインと機能を両立したアイテム。",
      "シーンを選ばず使えるシンプルな一品。",
      "日常をより快適にする、使いやすさを追求。"
    ],
    "brand_tone": "Honest_Wit"
  },
  {
    "cluster_id": 17,
    "persona": "default",
    "catch_copy": "iPhone14プラスケースで全方位を守るアルミバンパーの衝撃吸収力を実感しよう。 快適に使える高品質モデル。",
    "alts": [
      "シーンを選ばず使えるシンプルな一品。",
      "日常をより快適にする、使いやすさを追求。",
      "デザインと機能を両立したアイテム。",
      "シーンを選ばず使えるシンプルな一品。",
      "日常をより快適にする、使いやすさを追求。",
      "デザインと機能を両立したアイテム。",
      "シーンを選ばず使えるシンプルな一品。",
      "日常をより快適にする、使いやすさを追求。",
      "デザインと機能を両立したアイテム。",
      "シーンを選ばず使えるシンプルな一品。",
      "日常をより快適にする、使いやすさを追求。",
      "デザインと機能を両立したアイテム。",
      "シーンを選ばず使えるシンプルな一品。",
      "日常をより快適にする、使いやすさを追求。",
      "デザインと機能を両立したアイテム。",
      "シーンを選ばず使えるシンプルな一品。",
      "日常をより快適にする、使いやすさを追求。",
      "デザインと機能を両立したアイテム。",
      "シーンを選ばず使えるシンプルな一品。",
      "日常をより快適にする、使いやすさを追求。"
    ],
    "brand_tone": "Honest_Wit"
  },
  {
    "cluster_id": 18,
    "persona": "default",
    "catch_copy": "指紋がつかないさらさらフィルムで、快適操作を実現。 快適に使える高品質モデル。",
    "alts": [
      "シーンを選ばず使えるシンプルな一品。",
      "日常をより快適にする、使いやすさを追求。",
      "デザインと機能を両立したアイテム。",
      "シーンを選ばず使えるシンプルな一品。",
      "日常をより快適にする、使いやすさを追求。",
      "デザインと機能を両立したアイテム。",
      "シーンを選ばず使えるシンプルな一品。",
      "日常をより快適にする、使いやすさを追求。",
      "デザインと機能を両立したアイテム。",
      "シーンを選ばず使えるシンプルな一品。",
      "日常をより快適にする、使いやすさを追求。",
      "デザインと機能を両立したアイテム。",
      "シーンを選ばず使えるシンプルな一品。",
      "日常をより快適にする、使いやすさを追求。",
      "デザインと機能を両立したアイテム。",
      "シーンを選ばず使えるシンプルな一品。",
      "日常をより快適にする、使いやすさを追求。",
      "デザインと機能を両立したアイテム。",
      "シーンを選ばず使えるシンプルな一品。",
      "日常をより快適にする、使いやすさを追求。"
    ],
    "brand_tone": "Honest_Wit"
  },
  {
    "cluster_id": 19,
    "persona": "fashion_female",
    "catch_copy": "特別な日を彩る110cmのキッズドレスで可愛さ倍増。 快適に使える高品質モデル。",
    "alts": [
      "軽やかに日常を彩る、心ときめくデザイン。",
      "やさしい光をまとうような、上品な質感。",
      "自然体のあなたを引き立てる洗練されたスタイル。",
      "軽やかに日常を彩る、心ときめくデザイン。",
      "やさしい光をまとうような、上品な質感。",
      "自然体のあなたを引き立てる洗練されたスタイル。",
      "軽やかに日常を彩る、心ときめくデザイン。",
      "やさしい光をまとうような、上品な質感。",
      "自然体のあなたを引き立てる洗練されたスタイル。",
      "軽やかに日常を彩る、心ときめくデザイン。",
      "やさしい光をまとうような、上品な質感。",
      "自然体のあなたを引き立てる洗練されたスタイル。",
      "軽やかに日常を彩る、心ときめくデザイン。",
      "やさしい光をまとうような、上品な質感。",
      "自然体のあなたを引き立てる洗練されたスタイル。",
      "軽やかに日常を彩る、心ときめくデザイン。",
      "やさしい光をまとうような、上品な質感。",
      "自然体のあなたを引き立てる洗練されたスタイル。",
      "軽やかに日常を彩る、心ときめくデザイン。",
      "やさしい光をまとうような、上品な質感。"
    ],
    "brand_tone": "Honest_Wit"
  },
  {
    "cluster_id": 20,
    "persona": "default",
    "catch_copy": "アップルウォッチを守る高品質フィルムで、安心の毎日を手に入れよう。 快適に使える高品質モデル。",
    "alts": [
      "シーンを選ばず使えるシンプルな一品。",
      "日常をより快適にする、使いやすさを追求。",
      "デザインと機能を両立したアイテム。",
      "シーンを選ばず使えるシンプルな一品。",
      "日常をより快適にする、使いやすさを追求。",
      "デザインと機能を両立したアイテム。",
      "シーンを選ばず使えるシンプルな一品。",
      "日常をより快適にする、使いやすさを追求。",
      "デザインと機能を両立したアイテム。",
      "シーンを選ばず使えるシンプルな一品。",
      "日常をより快適にする、使いやすさを追求。",
      "デザインと機能を両立したアイテム。",
      "シーンを選ばず使えるシンプルな一品。",
      "日常をより快適にする、使いやすさを追求。",
      "デザインと機能を両立したアイテム。",
      "シーンを選ばず使えるシンプルな一品。",
      "日常をより快適にする、使いやすさを追求。",
      "デザインと機能を両立したアイテム。",
      "シーンを選ばず使えるシンプルな一品。",
      "日常をより快適にする、使いやすさを追求。"
    ],
    "brand_tone": "Honest_Wit"
  },
  {
    "cluster_id": 21,
    "persona": "tech_male",
    "catch_copy": "iPhone2台を同時充電急速3in1充電ケーブルの決定版。 快適に使える高品質モデル。",
    "alts": [
      "性能を研ぎ澄ませた一台、日々の効率を高める設計。",
      "スマートな操作感で、ビジネスもプライベートも快適に。",
      "機能美が光る、無駄のないデザイン。",
      "性能を研ぎ澄ませた一台、日々の効率を高める設計。",
      "スマートな操作感で、ビジネスもプライベートも快適に。",
      "機能美が光る、無駄のないデザイン。",
      "性能を研ぎ澄ませた一台、日々の効率を高める設計。",
      "スマートな操作感で、ビジネスもプライベートも快適に。",
      "機能美が光る、無駄のないデザイン。",
      "性能を研ぎ澄ませた一台、日々の効率を高める設計。",
      "スマートな操作感で、ビジネスもプライベートも快適に。",
      "機能美が光る、無駄のないデザイン。",
      "性能を研ぎ澄ませた一台、日々の効率を高める設計。",
      "スマートな操作感で、ビジネスもプライベートも快適に。",
      "機能美が光る、無駄のないデザイン。",
      "性能を研ぎ澄ませた一台、日々の効率を高める設計。",
      "スマートな操作感で、ビジネスもプライベートも快適に。",
      "機能美が光る、無駄のないデザイン。",
      "性能を研ぎ澄ませた一台、日々の効率を高める設計。",
      "スマートな操作感で、ビジネスもプライベートも快適に。"
    ],
    "brand_tone": "Honest_Wit"
  },
  {
    "cluster_id": 22,
    "persona": "tech_male",
    "catch_copy": "MacBookをしっかり守る高性能フィルムで快適な視界を手に入れよう。 快適に使える高品質モデル。",
    "alts": [
      "性能を研ぎ澄ませた一台、日々の効率を高める設計。",
      "スマートな操作感で、ビジネスもプライベートも快適に。",
      "機能美が光る、無駄のないデザイン。",
      "性能を研ぎ澄ませた一台、日々の効率を高める設計。",
      "スマートな操作感で、ビジネスもプライベートも快適に。",
      "機能美が光る、無駄のないデザイン。",
      "性能を研ぎ澄ませた一台、日々の効率を高める設計。",
      "スマートな操作感で、ビジネスもプライベートも快適に。",
      "機能美が光る、無駄のないデザイン。",
      "性能を研ぎ澄ませた一台、日々の効率を高める設計。",
      "スマートな操作感で、ビジネスもプライベートも快適に。",
      "機能美が光る、無駄のないデザイン。",
      "性能を研ぎ澄ませた一台、日々の効率を高める設計。",
      "スマートな操作感で、ビジネスもプライベートも快適に。",
      "機能美が光る、無駄のないデザイン。",
      "性能を研ぎ澄ませた一台、日々の効率を高める設計。",
      "スマートな操作感で、ビジネスもプライベートも快適に。",
      "機能美が光る、無駄のないデザイン。",
      "性能を研ぎ澄ませた一台、日々の効率を高める設計。",
      "スマートな操作感で、ビジネスもプライベートも快適に。"
    ],
    "brand_tone": "Honest_Wit"
  },
  {
    "cluster_id": 23,
    "persona": "fashion_female",
    "catch_copy": "さりげなく愛らしいデザインの小型扇風機で、涼しさを手に入れよう。 快適に使える高品質モデル。",
    "alts": [
      "軽やかに日常を彩る、心ときめくデザイン。",
      "やさしい光をまとうような、上品な質感。",
      "自然体のあなたを引き立てる洗練されたスタイル。",
      "軽やかに日常を彩る、心ときめくデザイン。",
      "やさしい光をまとうような、上品な質感。",
      "自然体のあなたを引き立てる洗練されたスタイル。",
      "軽やかに日常を彩る、心ときめくデザイン。",
      "やさしい光をまとうような、上品な質感。",
      "自然体のあなたを引き立てる洗練されたスタイル。",
      "軽やかに日常を彩る、心ときめくデザイン。",
      "やさしい光をまとうような、上品な質感。",
      "自然体のあなたを引き立てる洗練されたスタイル。",
      "軽やかに日常を彩る、心ときめくデザイン。",
      "やさしい光をまとうような、上品な質感。",
      "自然体のあなたを引き立てる洗練されたスタイル。",
      "軽やかに日常を彩る、心ときめくデザイン。",
      "やさしい光をまとうような、上品な質感。",
      "自然体のあなたを引き立てる洗練されたスタイル。",
      "軽やかに日常を彩る、心ときめくデザイン。",
      "やさしい光をまとうような、上品な質感。"
    ],
    "brand_tone": "Honest_Wit"
  },
  {
    "cluster_id": 24,
    "persona": "tech_male",
    "catch_copy": "旅行にぴったりの防水ポーチで、すべてをスマートに収納。 快適に使える高品質モデル。",
    "alts": [
      "性能を研ぎ澄ませた一台、日々の効率を高める設計。",
      "スマートな操作感で、ビジネスもプライベートも快適に。",
      "機能美が光る、無駄のないデザイン。",
      "性能を研ぎ澄ませた一台、日々の効率を高める設計。",
      "スマートな操作感で、ビジネスもプライベートも快適に。",
      "機能美が光る、無駄のないデザイン。",
      "性能を研ぎ澄ませた一台、日々の効率を高める設計。",
      "スマートな操作感で、ビジネスもプライベートも快適に。",
      "機能美が光る、無駄のないデザイン。",
      "性能を研ぎ澄ませた一台、日々の効率を高める設計。",
      "スマートな操作感で、ビジネスもプライベートも快適に。",
      "機能美が光る、無駄のないデザイン。",
      "性能を研ぎ澄ませた一台、日々の効率を高める設計。",
      "スマートな操作感で、ビジネスもプライベートも快適に。",
      "機能美が光る、無駄のないデザイン。",
      "性能を研ぎ澄ませた一台、日々の効率を高める設計。",
      "スマートな操作感で、ビジネスもプライベートも快適に。",
      "機能美が光る、無駄のないデザイン。",
      "性能を研ぎ澄ませた一台、日々の効率を高める設計。",
      "スマートな操作感で、ビジネスもプライベートも快適に。"
    ],
    "brand_tone": "Honest_Wit"
  },
  {
    "cluster_id": 25,
    "persona": "default",
    "catch_copy": "理にかなったシンプルさで上品で知的なおしゃれさな二つ折り財布。コンパクトで使いやすい。 快適に使える高品質モデル。",
    "alts": [
      "シーンを選ばず使えるシンプルな一品。",
      "日常をより快適にする、使いやすさを追求。",
      "デザインと機能を両立したアイテム。",
      "シーンを選ばず使えるシンプルな一品。",
      "日常をより快適にする、使いやすさを追求。",
      "デザインと機能を両立したアイテム。",
      "シーンを選ばず使えるシンプルな一品。",
      "日常をより快適にする、使いやすさを追求。",
      "デザインと機能を両立したアイテム。",
      "シーンを選ばず使えるシンプルな一品。",
      "日常をより快適にする、使いやすさを追求。",
      "デザインと機能を両立したアイテム。",
      "シーンを選ばず使えるシンプルな一品。",
      "日常をより快適にする、使いやすさを追求。",
      "デザインと機能を両立したアイテム。",
      "シーンを選ばず使えるシンプルな一品。",
      "日常をより快適にする、使いやすさを追求。",
      "デザインと機能を両立したアイテム。",
      "シーンを選ばず使えるシンプルな一品。",
      "日常をより快適にする、使いやすさを追求。"
    ],
    "brand_tone": "Honest_Wit"
  },
  {
    "cluster_id": 26,
    "persona": "tech_male",
    "catch_copy": "3台同時充電可能なワイヤレス充電器。スマホもApple Watchも、あっという間に急速充電。",
    "alts": [
      "性能を研ぎ澄ませた一台、日々の効率を高める設計。",
      "スマートな操作感で、ビジネスもプライベートも快適に。",
      "機能美が光る、無駄のないデザイン。",
      "性能を研ぎ澄ませた一台、日々の効率を高める設計。",
      "スマートな操作感で、ビジネスもプライベートも快適に。",
      "機能美が光る、無駄のないデザイン。",
      "性能を研ぎ澄ませた一台、日々の効率を高める設計。",
      "スマートな操作感で、ビジネスもプライベートも快適に。",
      "機能美が光る、無駄のないデザイン。",
      "性能を研ぎ澄ませた一台、日々の効率を高める設計。",
      "スマートな操作感で、ビジネスもプライベートも快適に。",
      "機能美が光る、無駄のないデザイン。",
      "性能を研ぎ澄ませた一台、日々の効率を高める設計。",
      "スマートな操作感で、ビジネスもプライベートも快適に。",
      "機能美が光る、無駄のないデザイン。",
      "性能を研ぎ澄ませた一台、日々の効率を高める設計。",
      "スマートな操作感で、ビジネスもプライベートも快適に。",
      "機能美が光る、無駄のないデザイン。",
      "性能を研ぎ澄ませた一台、日々の効率を高める設計。",
      "スマートな操作感で、ビジネスもプライベートも快適に。"
    ],
    "brand_tone": "Honest_Wit"
  },
  {
    "cluster_id": 27,
    "persona": "default",
    "catch_copy": "職人が丁寧に仕上げたエスニックなApple Watchバンド。 快適に使える高品質モデル。",
    "alts": [
      "シーンを選ばず使えるシンプルな一品。",
      "日常をより快適にする、使いやすさを追求。",
      "デザインと機能を両立したアイテム。",
      "シーンを選ばず使えるシンプルな一品。",
      "日常をより快適にする、使いやすさを追求。",
      "デザインと機能を両立したアイテム。",
      "シーンを選ばず使えるシンプルな一品。",
      "日常をより快適にする、使いやすさを追求。",
      "デザインと機能を両立したアイテム。",
      "シーンを選ばず使えるシンプルな一品。",
      "日常をより快適にする、使いやすさを追求。",
      "デザインと機能を両立したアイテム。",
      "シーンを選ばず使えるシンプルな一品。",
      "日常をより快適にする、使いやすさを追求。",
      "デザインと機能を両立したアイテム。",
      "シーンを選ばず使えるシンプルな一品。",
      "日常をより快適にする、使いやすさを追求。",
      "デザインと機能を両立したアイテム。",
      "シーンを選ばず使えるシンプルな一品。",
      "日常をより快適にする、使いやすさを追求。"
    ],
    "brand_tone": "Honest_Wit"
  },
  {
    "cluster_id": 28,
    "persona": "tech_male",
    "catch_copy": "iPhoneを素早く充電するワイヤレス充電器で、快適な毎日を。 快適に使える高品質モデル。",
    "alts": [
      "性能を研ぎ澄ませた一台、日々の効率を高める設計。",
      "スマートな操作感で、ビジネスもプライベートも快適に。",
      "機能美が光る、無駄のないデザイン。",
      "性能を研ぎ澄ませた一台、日々の効率を高める設計。",
      "スマートな操作感で、ビジネスもプライベートも快適に。",
      "機能美が光る、無駄のないデザイン。",
      "性能を研ぎ澄ませた一台、日々の効率を高める設計。",
      "スマートな操作感で、ビジネスもプライベートも快適に。",
      "機能美が光る、無駄のないデザイン。",
      "性能を研ぎ澄ませた一台、日々の効率を高める設計。",
      "スマートな操作感で、ビジネスもプライベートも快適に。",
      "機能美が光る、無駄のないデザイン。",
      "性能を研ぎ澄ませた一台、日々の効率を高める設計。",
      "スマートな操作感で、ビジネスもプライベートも快適に。",
      "機能美が光る、無駄のないデザイン。",
      "性能を研ぎ澄ませた一台、日々の効率を高める設計。",
      "スマートな操作感で、ビジネスもプライベートも快適に。",
      "機能美が光る、無駄のないデザイン。",
      "性能を研ぎ澄ませた一台、日々の効率を高める設計。",
      "スマートな操作感で、ビジネスもプライベートも快適に。"
    ],
    "brand_tone": "Honest_Wit"
  },
  {
    "cluster_id": 29,
    "persona": "default",
    "catch_copy": "iPhone14Plusを守る、スタイリッシュなクリアケース。 快適に使える高品質モデル。",
    "alts": [
      "シーンを選ばず使えるシンプルな一品。",
      "日常をより快適にする、使いやすさを追求。",
      "デザインと機能を両立したアイテム。",
      "シーンを選ばず使えるシンプルな一品。",
      "日常をより快適にする、使いやすさを追求。",
      "デザインと機能を両立したアイテム。",
      "シーンを選ばず使えるシンプルな一品。",
      "日常をより快適にする、使いやすさを追求。",
      "デザインと機能を両立したアイテム。",
      "シーンを選ばず使えるシンプルな一品。",
      "日常をより快適にする、使いやすさを追求。",
      "デザインと機能を両立したアイテム。",
      "シーンを選ばず使えるシンプルな一品。",
      "日常をより快適にする、使いやすさを追求。",
      "デザインと機能を両立したアイテム。",
      "シーンを選ばず使えるシンプルな一品。",
      "日常をより快適にする、使いやすさを追求。",
      "デザインと機能を両立したアイテム。",
      "シーンを選ばず使えるシンプルな一品。",
      "日常をより快適にする、使いやすさを追求。"
    ],
    "brand_tone": "Honest_Wit"
  },
  {
    "cluster_id": 30,
    "persona": "default",
    "catch_copy": "アップルウォッチを守る簡単取り付けの保護シール2枚セット。 快適に使える高品質モデル。",
    "alts": [
      "シーンを選ばず使えるシンプルな一品。",
      "日常をより快適にする、使いやすさを追求。",
      "デザインと機能を両立したアイテム。",
      "シーンを選ばず使えるシンプルな一品。",
      "日常をより快適にする、使いやすさを追求。",
      "デザインと機能を両立したアイテム。",
      "シーンを選ばず使えるシンプルな一品。",
      "日常をより快適にする、使いやすさを追求。",
      "デザインと機能を両立したアイテム。",
      "シーンを選ばず使えるシンプルな一品。",
      "日常をより快適にする、使いやすさを追求。",
      "デザインと機能を両立したアイテム。",
      "シーンを選ばず使えるシンプルな一品。",
      "日常をより快適にする、使いやすさを追求。",
      "デザインと機能を両立したアイテム。",
      "シーンを選ばず使えるシンプルな一品。",
      "日常をより快適にする、使いやすさを追求。",
      "デザインと機能を両立したアイテム。",
      "シーンを選ばず使えるシンプルな一品。",
      "日常をより快適にする、使いやすさを追求。"
    ],
    "brand_tone": "Honest_Wit"
  },
  {
    "cluster_id": 31,
    "persona": "office",
    "catch_copy": "ビジネスシーンにも最適なレザー製アップルウォッチバンド。 快適に使える高品質モデル。",
    "alts": [
      "洗練された印象を与える、知的なデザイン。",
      "毎日の業務をスマートに支える実用性。",
      "オフィスワークに心地よい集中環境を提供。",
      "洗練された印象を与える、知的なデザイン。",
      "毎日の業務をスマートに支える実用性。",
      "オフィスワークに心地よい集中環境を提供。",
      "洗練された印象を与える、知的なデザイン。",
      "毎日の業務をスマートに支える実用性。",
      "オフィスワークに心地よい集中環境を提供。",
      "洗練された印象を与える、知的なデザイン。",
      "毎日の業務をスマートに支える実用性。",
      "オフィスワークに心地よい集中環境を提供。",
      "洗練された印象を与える、知的なデザイン。",
      "毎日の業務をスマートに支える実用性。",
      "オフィスワークに心地よい集中環境を提供。",
      "洗練された印象を与える、知的なデザイン。",
      "毎日の業務をスマートに支える実用性。",
      "オフィスワークに心地よい集中環境を提供。",
      "洗練された印象を与える、知的なデザイン。",
      "毎日の業務をスマートに支える実用性。"
    ],
    "brand_tone": "Honest_Wit"
  },
  {
    "cluster_id": 32,
    "persona": "tech_male",
    "catch_copy": "スタイリッシュなiPhoneケースで、カード収納もスマートに。 快適に使える高品質モデル。",
    "alts": [
      "性能を研ぎ澄ませた一台、日々の効率を高める設計。",
      "スマートな操作感で、ビジネスもプライベートも快適に。",
      "機能美が光る、無駄のないデザイン。",
      "性能を研ぎ澄ませた一台、日々の効率を高める設計。",
      "スマートな操作感で、ビジネスもプライベートも快適に。",
      "機能美が光る、無駄のないデザイン。",
      "性能を研ぎ澄ませた一台、日々の効率を高める設計。",
      "スマートな操作感で、ビジネスもプライベートも快適に。",
      "機能美が光る、無駄のないデザイン。",
      "性能を研ぎ澄ませた一台、日々の効率を高める設計。",
      "スマートな操作感で、ビジネスもプライベートも快適に。",
      "機能美が光る、無駄のないデザイン。",
      "性能を研ぎ澄ませた一台、日々の効率を高める設計。",
      "スマートな操作感で、ビジネスもプライベートも快適に。",
      "機能美が光る、無駄のないデザイン。",
      "性能を研ぎ澄ませた一台、日々の効率を高める設計。",
      "スマートな操作感で、ビジネスもプライベートも快適に。",
      "機能美が光る、無駄のないデザイン。",
      "性能を研ぎ澄ませた一台、日々の効率を高める設計。",
      "スマートな操作感で、ビジネスもプライベートも快適に。"
    ],
    "brand_tone": "Honest_Wit"
  },
  {
    "cluster_id": 33,
    "persona": "default",
    "catch_copy": "静かに上質を感じさせる感あふれるアップルウォッチバンドで上品で知的なおしゃれさを楽しもう。 快適に使える高品質モデル。",
    "alts": [
      "シーンを選ばず使えるシンプルな一品。",
      "日常をより快適にする、使いやすさを追求。",
      "デザインと機能を両立したアイテム。",
      "シーンを選ばず使えるシンプルな一品。",
      "日常をより快適にする、使いやすさを追求。",
      "デザインと機能を両立したアイテム。",
      "シーンを選ばず使えるシンプルな一品。",
      "日常をより快適にする、使いやすさを追求。",
      "デザインと機能を両立したアイテム。",
      "シーンを選ばず使えるシンプルな一品。",
      "日常をより快適にする、使いやすさを追求。",
      "デザインと機能を両立したアイテム。",
      "シーンを選ばず使えるシンプルな一品。",
      "日常をより快適にする、使いやすさを追求。",
      "デザインと機能を両立したアイテム。",
      "シーンを選ばず使えるシンプルな一品。",
      "日常をより快適にする、使いやすさを追求。",
      "デザインと機能を両立したアイテム。",
      "シーンを選ばず使えるシンプルな一品。",
      "日常をより快適にする、使いやすさを追求。"
    ],
    "brand_tone": "Honest_Wit"
  },
  {
    "cluster_id": 34,
    "persona": "default",
    "catch_copy": "iPhone14ケースで全方位を守る、薄型軽量のフルカバーを手に入れよう。 快適に使える高品質モデル。",
    "alts": [
      "シーンを選ばず使えるシンプルな一品。",
      "日常をより快適にする、使いやすさを追求。",
      "デザインと機能を両立したアイテム。",
      "シーンを選ばず使えるシンプルな一品。",
      "日常をより快適にする、使いやすさを追求。",
      "デザインと機能を両立したアイテム。",
      "シーンを選ばず使えるシンプルな一品。",
      "日常をより快適にする、使いやすさを追求。",
      "デザインと機能を両立したアイテム。",
      "シーンを選ばず使えるシンプルな一品。",
      "日常をより快適にする、使いやすさを追求。",
      "デザインと機能を両立したアイテム。",
      "シーンを選ばず使えるシンプルな一品。",
      "日常をより快適にする、使いやすさを追求。",
      "デザインと機能を両立したアイテム。",
      "シーンを選ばず使えるシンプルな一品。",
      "日常をより快適にする、使いやすさを追求。",
      "デザインと機能を両立したアイテム。",
      "シーンを選ばず使えるシンプルな一品。",
      "日常をより快適にする、使いやすさを追求。"
    ],
    "brand_tone": "Honest_Wit"
  },
  {
    "cluster_id": 35,
    "persona": "default",
    "catch_copy": "アップルウォッチを華やかに彩るパールバンド。 快適に使える高品質モデル。",
    "alts": [
      "シーンを選ばず使えるシンプルな一品。",
      "日常をより快適にする、使いやすさを追求。",
      "デザインと機能を両立したアイテム。",
      "シーンを選ばず使えるシンプルな一品。",
      "日常をより快適にする、使いやすさを追求。",
      "デザインと機能を両立したアイテム。",
      "シーンを選ばず使えるシンプルな一品。",
      "日常をより快適にする、使いやすさを追求。",
      "デザインと機能を両立したアイテム。",
      "シーンを選ばず使えるシンプルな一品。",
      "日常をより快適にする、使いやすさを追求。",
      "デザインと機能を両立したアイテム。",
      "シーンを選ばず使えるシンプルな一品。",
      "日常をより快適にする、使いやすさを追求。",
      "デザインと機能を両立したアイテム。",
      "シーンを選ばず使えるシンプルな一品。",
      "日常をより快適にする、使いやすさを追求。",
      "デザインと機能を両立したアイテム。",
      "シーンを選ばず使えるシンプルな一品。",
      "日常をより快適にする、使いやすさを追求。"
    ],
    "brand_tone": "Honest_Wit"
  },
  {
    "cluster_id": 36,
    "persona": "default",
    "catch_copy": "女性のための華やかなフォーマルアップルウォッチバンド。 快適に使える高品質モデル。",
    "alts": [
      "シーンを選ばず使えるシンプルな一品。",
      "日常をより快適にする、使いやすさを追求。",
      "デザインと機能を両立したアイテム。",
      "シーンを選ばず使えるシンプルな一品。",
      "日常をより快適にする、使いやすさを追求。",
      "デザインと機能を両立したアイテム。",
      "シーンを選ばず使えるシンプルな一品。",
      "日常をより快適にする、使いやすさを追求。",
      "デザインと機能を両立したアイテム。",
      "シーンを選ばず使えるシンプルな一品。",
      "日常をより快適にする、使いやすさを追求。",
      "デザインと機能を両立したアイテム。",
      "シーンを選ばず使えるシンプルな一品。",
      "日常をより快適にする、使いやすさを追求。",
      "デザインと機能を両立したアイテム。",
      "シーンを選ばず使えるシンプルな一品。",
      "日常をより快適にする、使いやすさを追求。",
      "デザインと機能を両立したアイテム。",
      "シーンを選ばず使えるシンプルな一品。",
      "日常をより快適にする、使いやすさを追求。"
    ],
    "brand_tone": "Honest_Wit"
  },
  {
    "cluster_id": 37,
    "persona": "fashion_female",
    "catch_copy": "大人さりげなく愛らしいiPhoneケースで肩掛けスタイルを楽しもう。 快適に使える高品質モデル。",
    "alts": [
      "軽やかに日常を彩る、心ときめくデザイン。",
      "やさしい光をまとうような、上品な質感。",
      "自然体のあなたを引き立てる洗練されたスタイル。",
      "軽やかに日常を彩る、心ときめくデザイン。",
      "やさしい光をまとうような、上品な質感。",
      "自然体のあなたを引き立てる洗練されたスタイル。",
      "軽やかに日常を彩る、心ときめくデザイン。",
      "やさしい光をまとうような、上品な質感。",
      "自然体のあなたを引き立てる洗練されたスタイル。",
      "軽やかに日常を彩る、心ときめくデザイン。",
      "やさしい光をまとうような、上品な質感。",
      "自然体のあなたを引き立てる洗練されたスタイル。",
      "軽やかに日常を彩る、心ときめくデザイン。",
      "やさしい光をまとうような、上品な質感。",
      "自然体のあなたを引き立てる洗練されたスタイル。",
      "軽やかに日常を彩る、心ときめくデザイン。",
      "やさしい光をまとうような、上品な質感。",
      "自然体のあなたを引き立てる洗練されたスタイル。",
      "軽やかに日常を彩る、心ときめくデザイン。",
      "やさしい光をまとうような、上品な質感。"
    ],
    "brand_tone": "Honest_Wit"
  },
  {
    "cluster_id": 38,
    "persona": "office",
    "catch_copy": "ビジネスシーンにぴったりの15.6インチ対応リュック。 快適に使える高品質モデル。",
    "alts": [
      "洗練された印象を与える、知的なデザイン。",
      "毎日の業務をスマートに支える実用性。",
      "オフィスワークに心地よい集中環境を提供。",
      "洗練された印象を与える、知的なデザイン。",
      "毎日の業務をスマートに支える実用性。",
      "オフィスワークに心地よい集中環境を提供。",
      "洗練された印象を与える、知的なデザイン。",
      "毎日の業務をスマートに支える実用性。",
      "オフィスワークに心地よい集中環境を提供。",
      "洗練された印象を与える、知的なデザイン。",
      "毎日の業務をスマートに支える実用性。",
      "オフィスワークに心地よい集中環境を提供。",
      "洗練された印象を与える、知的なデザイン。",
      "毎日の業務をスマートに支える実用性。",
      "オフィスワークに心地よい集中環境を提供。",
      "洗練された印象を与える、知的なデザイン。",
      "毎日の業務をスマートに支える実用性。",
      "オフィスワークに心地よい集中環境を提供。",
      "洗練された印象を与える、知的なデザイン。",
      "毎日の業務をスマートに支える実用性。"
    ],
    "brand_tone": "Honest_Wit"
  },
  {
    "cluster_id": 39,
    "persona": "default",
    "catch_copy": "iPhoneを守る覗き見防止ガラスフィルムで、プライバシーを守ろう。 快適に使える高品質モデル。",
    "alts": [
      "シーンを選ばず使えるシンプルな一品。",
      "日常をより快適にする、使いやすさを追求。",
      "デザインと機能を両立したアイテム。",
      "シーンを選ばず使えるシンプルな一品。",
      "日常をより快適にする、使いやすさを追求。",
      "デザインと機能を両立したアイテム。",
      "シーンを選ばず使えるシンプルな一品。",
      "日常をより快適にする、使いやすさを追求。",
      "デザインと機能を両立したアイテム。",
      "シーンを選ばず使えるシンプルな一品。",
      "日常をより快適にする、使いやすさを追求。",
      "デザインと機能を両立したアイテム。",
      "シーンを選ばず使えるシンプルな一品。",
      "日常をより快適にする、使いやすさを追求。",
      "デザインと機能を両立したアイテム。",
      "シーンを選ばず使えるシンプルな一品。",
      "日常をより快適にする、使いやすさを追求。",
      "デザインと機能を両立したアイテム。",
      "シーンを選ばず使えるシンプルな一品。",
      "日常をより快適にする、使いやすさを追求。"
    ],
    "brand_tone": "Honest_Wit"
  },
  {
    "cluster_id": 40,
    "persona": "tech_male",
    "catch_copy": "iPhone14ProMaxを守る、スタイリッシュなMagSafe充電対応ケース。 快適に使える高品質モデル。",
    "alts": [
      "性能を研ぎ澄ませた一台、日々の効率を高める設計。",
      "スマートな操作感で、ビジネスもプライベートも快適に。",
      "機能美が光る、無駄のないデザイン。",
      "性能を研ぎ澄ませた一台、日々の効率を高める設計。",
      "スマートな操作感で、ビジネスもプライベートも快適に。",
      "機能美が光る、無駄のないデザイン。",
      "性能を研ぎ澄ませた一台、日々の効率を高める設計。",
      "スマートな操作感で、ビジネスもプライベートも快適に。",
      "機能美が光る、無駄のないデザイン。",
      "性能を研ぎ澄ませた一台、日々の効率を高める設計。",
      "スマートな操作感で、ビジネスもプライベートも快適に。",
      "機能美が光る、無駄のないデザイン。",
      "性能を研ぎ澄ませた一台、日々の効率を高める設計。",
      "スマートな操作感で、ビジネスもプライベートも快適に。",
      "機能美が光る、無駄のないデザイン。",
      "性能を研ぎ澄ませた一台、日々の効率を高める設計。",
      "スマートな操作感で、ビジネスもプライベートも快適に。",
      "機能美が光る、無駄のないデザイン。",
      "性能を研ぎ澄ませた一台、日々の効率を高める設計。",
      "スマートな操作感で、ビジネスもプライベートも快適に。"
    ],
    "brand_tone": "Honest_Wit"
  },
  {
    "cluster_id": 41,
    "persona": "default",
    "catch_copy": "確定申告もこれ一台マイナンバー対応ICカードリーダー。 快適に使える高品質モデル。",
    "alts": [
      "シーンを選ばず使えるシンプルな一品。",
      "日常をより快適にする、使いやすさを追求。",
      "デザインと機能を両立したアイテム。",
      "シーンを選ばず使えるシンプルな一品。",
      "日常をより快適にする、使いやすさを追求。",
      "デザインと機能を両立したアイテム。",
      "シーンを選ばず使えるシンプルな一品。",
      "日常をより快適にする、使いやすさを追求。",
      "デザインと機能を両立したアイテム。",
      "シーンを選ばず使えるシンプルな一品。",
      "日常をより快適にする、使いやすさを追求。",
      "デザインと機能を両立したアイテム。",
      "シーンを選ばず使えるシンプルな一品。",
      "日常をより快適にする、使いやすさを追求。",
      "デザインと機能を両立したアイテム。",
      "シーンを選ばず使えるシンプルな一品。",
      "日常をより快適にする、使いやすさを追求。",
      "デザインと機能を両立したアイテム。",
      "シーンを選ばず使えるシンプルな一品。",
      "日常をより快適にする、使いやすさを追求。"
    ],
    "brand_tone": "Honest_Wit"
  },
  {
    "cluster_id": 42,
    "persona": "tech_male",
    "catch_copy": "MicroUSBはもう不要急速充電対応の3in1マルチケーブル。 快適に使える高品質モデル。",
    "alts": [
      "性能を研ぎ澄ませた一台、日々の効率を高める設計。",
      "スマートな操作感で、ビジネスもプライベートも快適に。",
      "機能美が光る、無駄のないデザイン。",
      "性能を研ぎ澄ませた一台、日々の効率を高める設計。",
      "スマートな操作感で、ビジネスもプライベートも快適に。",
      "機能美が光る、無駄のないデザイン。",
      "性能を研ぎ澄ませた一台、日々の効率を高める設計。",
      "スマートな操作感で、ビジネスもプライベートも快適に。",
      "機能美が光る、無駄のないデザイン。",
      "性能を研ぎ澄ませた一台、日々の効率を高める設計。",
      "スマートな操作感で、ビジネスもプライベートも快適に。",
      "機能美が光る、無駄のないデザイン。",
      "性能を研ぎ澄ませた一台、日々の効率を高める設計。",
      "スマートな操作感で、ビジネスもプライベートも快適に。",
      "機能美が光る、無駄のないデザイン。",
      "性能を研ぎ澄ませた一台、日々の効率を高める設計。",
      "スマートな操作感で、ビジネスもプライベートも快適に。",
      "機能美が光る、無駄のないデザイン。",
      "性能を研ぎ澄ませた一台、日々の効率を高める設計。",
      "スマートな操作感で、ビジネスもプライベートも快適に。"
    ],
    "brand_tone": "Honest_Wit"
  },
  {
    "cluster_id": 43,
    "persona": "default",
    "catch_copy": "ギャラクシーA22 5GとS21を守る、耐衝撃手帳型カバー登場。 快適に使える高品質モデル。",
    "alts": [
      "シーンを選ばず使えるシンプルな一品。",
      "日常をより快適にする、使いやすさを追求。",
      "デザインと機能を両立したアイテム。",
      "シーンを選ばず使えるシンプルな一品。",
      "日常をより快適にする、使いやすさを追求。",
      "デザインと機能を両立したアイテム。",
      "シーンを選ばず使えるシンプルな一品。",
      "日常をより快適にする、使いやすさを追求。",
      "デザインと機能を両立したアイテム。",
      "シーンを選ばず使えるシンプルな一品。",
      "日常をより快適にする、使いやすさを追求。",
      "デザインと機能を両立したアイテム。",
      "シーンを選ばず使えるシンプルな一品。",
      "日常をより快適にする、使いやすさを追求。",
      "デザインと機能を両立したアイテム。",
      "シーンを選ばず使えるシンプルな一品。",
      "日常をより快適にする、使いやすさを追求。",
      "デザインと機能を両立したアイテム。",
      "シーンを選ばず使えるシンプルな一品。",
      "日常をより快適にする、使いやすさを追求。"
    ],
    "brand_tone": "Honest_Wit"
  },
  {
    "cluster_id": 44,
    "persona": "default",
    "catch_copy": "Xperia 5 IIをスタイリッシュに守る手帳型ケース。 快適に使える高品質モデル。",
    "alts": [
      "シーンを選ばず使えるシンプルな一品。",
      "日常をより快適にする、使いやすさを追求。",
      "デザインと機能を両立したアイテム。",
      "シーンを選ばず使えるシンプルな一品。",
      "日常をより快適にする、使いやすさを追求。",
      "デザインと機能を両立したアイテム。",
      "シーンを選ばず使えるシンプルな一品。",
      "日常をより快適にする、使いやすさを追求。",
      "デザインと機能を両立したアイテム。",
      "シーンを選ばず使えるシンプルな一品。",
      "日常をより快適にする、使いやすさを追求。",
      "デザインと機能を両立したアイテム。",
      "シーンを選ばず使えるシンプルな一品。",
      "日常をより快適にする、使いやすさを追求。",
      "デザインと機能を両立したアイテム。",
      "シーンを選ばず使えるシンプルな一品。",
      "日常をより快適にする、使いやすさを追求。",
      "デザインと機能を両立したアイテム。",
      "シーンを選ばず使えるシンプルな一品。",
      "日常をより快適にする、使いやすさを追求。"
    ],
    "brand_tone": "Honest_Wit"
  },
  {
    "cluster_id": 45,
    "persona": "default",
    "catch_copy": "マグセーフ対応の手帳型iPhoneケースで、スタイリッシュに決めよう。 快適に使える高品質モデル。",
    "alts": [
      "シーンを選ばず使えるシンプルな一品。",
      "日常をより快適にする、使いやすさを追求。",
      "デザインと機能を両立したアイテム。",
      "シーンを選ばず使えるシンプルな一品。",
      "日常をより快適にする、使いやすさを追求。",
      "デザインと機能を両立したアイテム。",
      "シーンを選ばず使えるシンプルな一品。",
      "日常をより快適にする、使いやすさを追求。",
      "デザインと機能を両立したアイテム。",
      "シーンを選ばず使えるシンプルな一品。",
      "日常をより快適にする、使いやすさを追求。",
      "デザインと機能を両立したアイテム。",
      "シーンを選ばず使えるシンプルな一品。",
      "日常をより快適にする、使いやすさを追求。",
      "デザインと機能を両立したアイテム。",
      "シーンを選ばず使えるシンプルな一品。",
      "日常をより快適にする、使いやすさを追求。",
      "デザインと機能を両立したアイテム。",
      "シーンを選ばず使えるシンプルな一品。",
      "日常をより快適にする、使いやすさを追求。"
    ],
    "brand_tone": "Honest_Wit"
  },
  {
    "cluster_id": 46,
    "persona": "tech_male",
    "catch_copy": "iPhone17対応180度回転で使いやすい高速Type-Cケーブル2m。 快適に使える高品質モデル。",
    "alts": [
      "性能を研ぎ澄ませた一台、日々の効率を高める設計。",
      "スマートな操作感で、ビジネスもプライベートも快適に。",
      "機能美が光る、無駄のないデザイン。",
      "性能を研ぎ澄ませた一台、日々の効率を高める設計。",
      "スマートな操作感で、ビジネスもプライベートも快適に。",
      "機能美が光る、無駄のないデザイン。",
      "性能を研ぎ澄ませた一台、日々の効率を高める設計。",
      "スマートな操作感で、ビジネスもプライベートも快適に。",
      "機能美が光る、無駄のないデザイン。",
      "性能を研ぎ澄ませた一台、日々の効率を高める設計。",
      "スマートな操作感で、ビジネスもプライベートも快適に。",
      "機能美が光る、無駄のないデザイン。",
      "性能を研ぎ澄ませた一台、日々の効率を高める設計。",
      "スマートな操作感で、ビジネスもプライベートも快適に。",
      "機能美が光る、無駄のないデザイン。",
      "性能を研ぎ澄ませた一台、日々の効率を高める設計。",
      "スマートな操作感で、ビジネスもプライベートも快適に。",
      "機能美が光る、無駄のないデザイン。",
      "性能を研ぎ澄ませた一台、日々の効率を高める設計。",
      "スマートな操作感で、ビジネスもプライベートも快適に。"
    ],
    "brand_tone": "Honest_Wit"
  },
  {
    "cluster_id": 47,
    "persona": "tech_male",
    "catch_copy": "楽天1位USB4ケーブルで超高速データ転送と急速充電を実現。 快適に使える高品質モデル。",
    "alts": [
      "性能を研ぎ澄ませた一台、日々の効率を高める設計。",
      "スマートな操作感で、ビジネスもプライベートも快適に。",
      "機能美が光る、無駄のないデザイン。",
      "性能を研ぎ澄ませた一台、日々の効率を高める設計。",
      "スマートな操作感で、ビジネスもプライベートも快適に。",
      "機能美が光る、無駄のないデザイン。",
      "性能を研ぎ澄ませた一台、日々の効率を高める設計。",
      "スマートな操作感で、ビジネスもプライベートも快適に。",
      "機能美が光る、無駄のないデザイン。",
      "性能を研ぎ澄ませた一台、日々の効率を高める設計。",
      "スマートな操作感で、ビジネスもプライベートも快適に。",
      "機能美が光る、無駄のないデザイン。",
      "性能を研ぎ澄ませた一台、日々の効率を高める設計。",
      "スマートな操作感で、ビジネスもプライベートも快適に。",
      "機能美が光る、無駄のないデザイン。",
      "性能を研ぎ澄ませた一台、日々の効率を高める設計。",
      "スマートな操作感で、ビジネスもプライベートも快適に。",
      "機能美が光る、無駄のないデザイン。",
      "性能を研ぎ澄ませた一台、日々の効率を高める設計。",
      "スマートな操作感で、ビジネスもプライベートも快適に。"
    ],
    "brand_tone": "Honest_Wit"
  },
  {
    "cluster_id": 48,
    "persona": "tech_male",
    "catch_copy": "楽天1位のThunderboltケーブルで、高速充電と映像出力を手に入れよう。 快適に使える高品質モデル。",
    "alts": [
      "性能を研ぎ澄ませた一台、日々の効率を高める設計。",
      "スマートな操作感で、ビジネスもプライベートも快適に。",
      "機能美が光る、無駄のないデザイン。",
      "性能を研ぎ澄ませた一台、日々の効率を高める設計。",
      "スマートな操作感で、ビジネスもプライベートも快適に。",
      "機能美が光る、無駄のないデザイン。",
      "性能を研ぎ澄ませた一台、日々の効率を高める設計。",
      "スマートな操作感で、ビジネスもプライベートも快適に。",
      "機能美が光る、無駄のないデザイン。",
      "性能を研ぎ澄ませた一台、日々の効率を高める設計。",
      "スマートな操作感で、ビジネスもプライベートも快適に。",
      "機能美が光る、無駄のないデザイン。",
      "性能を研ぎ澄ませた一台、日々の効率を高める設計。",
      "スマートな操作感で、ビジネスもプライベートも快適に。",
      "機能美が光る、無駄のないデザイン。",
      "性能を研ぎ澄ませた一台、日々の効率を高める設計。",
      "スマートな操作感で、ビジネスもプライベートも快適に。",
      "機能美が光る、無駄のないデザイン。",
      "性能を研ぎ澄ませた一台、日々の効率を高める設計。",
      "スマートな操作感で、ビジネスもプライベートも快適に。"
    ],
    "brand_tone": "Honest_Wit"
  },
  {
    "cluster_id": 49,
    "persona": "tech_male",
    "catch_copy": "オフィスで快適に使える3in1タイプCケーブル。 快適に使える高品質モデル。",
    "alts": [
      "性能を研ぎ澄ませた一台、日々の効率を高める設計。",
      "スマートな操作感で、ビジネスもプライベートも快適に。",
      "機能美が光る、無駄のないデザイン。",
      "性能を研ぎ澄ませた一台、日々の効率を高める設計。",
      "スマートな操作感で、ビジネスもプライベートも快適に。",
      "機能美が光る、無駄のないデザイン。",
      "性能を研ぎ澄ませた一台、日々の効率を高める設計。",
      "スマートな操作感で、ビジネスもプライベートも快適に。",
      "機能美が光る、無駄のないデザイン。",
      "性能を研ぎ澄ませた一台、日々の効率を高める設計。",
      "スマートな操作感で、ビジネスもプライベートも快適に。",
      "機能美が光る、無駄のないデザイン。",
      "性能を研ぎ澄ませた一台、日々の効率を高める設計。",
      "スマートな操作感で、ビジネスもプライベートも快適に。",
      "機能美が光る、無駄のないデザイン。",
      "性能を研ぎ澄ませた一台、日々の効率を高める設計。",
      "スマートな操作感で、ビジネスもプライベートも快適に。",
      "機能美が光る、無駄のないデザイン。",
      "性能を研ぎ澄ませた一台、日々の効率を高める設計。",
      "スマートな操作感で、ビジネスもプライベートも快適に。"
    ],
    "brand_tone": "Honest_Wit"
  }
]